capsule_downloader.py
capsule_downloader-1.0.1.dist-info/entry_points.txt
capsule_downloader-1.0.1.dist-info/WHEEL
capsule_downloader-1.0.1.dist-info/METADATA
capsule_downloader-1.0.1.dist-info/RECORD
